{"info":{"symbol":"ASIANPAINT","companyName":"Asian Paints Limited","industry":"PAINTS","activeSeries":["EQ"],"debtSeries":[],"tempSuspendedSeries":[],"isFNOSec":true,"isCASec":false,"isSLBSec":true,"isDebtSec":false,"isSuspended":false,"isETFSec":false,"isDelisted":false,"isin":"INE021A01026","isTop10":false,"identifier":"ASIANPAINTEQN"},"metadata":{"series":"EQ","symbol":"ASIANPAINT","isin":"INE021A01026","status":"Listed","listingDate":"31-May-1995","industry":"PAINTS","lastUpdateTime":"12-May-2021 11:59:16","pdSectorPe":33.57,"pdSymbolPe":91.32,"pdSectorInd":"NIFTY 500                                         "},"securityInfo":{"boardStatus":"Main","tradingStatus":"Active","tradingSegment":"Normal Market","sessionNo":"-","slb":"Yes","classOfShare":"Equity","derivatives":"Yes","surveillance":"-","faceValue":1,"issuedCap":959197790},"priceInfo":{"lastPrice":2573.9,"change":17.65000000000009,"pChange":0.6904645476772652,"previousClose":2556.25,"open":2577,"close":0,"vwap":2571.02,"lowerCP":"2300.65","upperCP":"2811.85","pPriceBand":"No Band","basePrice":2556.25,"intraDayHighLow":{"min":2548.2,"max":2588.95,"value":2573.9},"weekHighLow":{"min":1482.95,"minDate":"19-May-2020","max":2873.45,"maxDate":"11-Jan-2021","value":2573.9}},"preOpenMarket":{"preopen":[{"price":2300.65,"buyQty":0,"sellQty":34},{"price":2326.2,"buyQty":0,"sellQty":390},{"price":2428.45,"buyQty":0,"sellQty":481},{"price":2441.25,"buyQty":0,"sellQty":13},{"price":2577,"buyQty":0,"sellQty":0,"iep":true},{"price":2643.25,"buyQty":440,"sellQty":0},{"price":2644.8,"buyQty":180,"sellQty":0},{"price":2680,"buyQty":1,"sellQty":0},{"price":2684.05,"buyQty":1525,"sellQty":0}],"ato":{"buy":4590,"sell":586},"IEP":2577,"totalTradedVolume":7645,"finalPrice":2577,"finalQuantity":7645,"lastUpdateTime":"12-May-2021 09:07:06","totalBuyQuantity":25704,"totalSellQuantity":35817,"atoBuyQty":4590,"atoSellQty":586}}